pyfeeds/__init__.py
pyfeeds/__main__.py
pyfeeds/common.py
pyfeeds/evaluate.py
pyfeeds/hashing.py
pyfeeds/imagecache.py
pyfeeds/main.py
pyfeeds/testing.py
pyfeeds/tests/__init__.py
pyfeeds/tests/test_evaluate.py
pyfeeds/tests/test_hashing.py
pyfeeds/tests/test_testing.py
fsl_pyfeeds-0.9.5.dist-info/LICENSE
fsl_pyfeeds-0.9.5.dist-info/METADATA
fsl_pyfeeds-0.9.5.dist-info/WHEEL
fsl_pyfeeds-0.9.5.dist-info/entry_points.txt
fsl_pyfeeds-0.9.5.dist-info/top_level.txt
fsl_pyfeeds-0.9.5.dist-info/RECORD
