Metadata-Version: 2.1
Name: fsl-pyfeeds
Version: 0.9.5
Summary: FSL testing framework
Home-page: https://git.fmrib.ox.ac.uk/fsl/pyfeeds
Author: Paul McCarthy
Author-email: pauldmccarthy@gmail.com
License: Apache License Version 2.0
Platform: UNKNOWN
Classifier: Development Status :: 3 - Alpha
Classifier: Intended Audience :: Developers
Classifier: License :: Free for non-commercial use
Classifier: Programming Language :: Python :: 3.5
Classifier: Programming Language :: Python :: 3.6
Classifier: Programming Language :: Python :: 3.7
Classifier: Topic :: Software Development :: Libraries :: Python Modules
Requires-Dist: numpy (>=1.11.1)
Requires-Dist: nibabel (>=2.1.0)
